mimm/__init__.py
mimm/models/__init__.py
mimm/models/_registry.py
mimm/models/shared_layers.py
mimm/models/utils.py
mimm/models/classification/__init__.py
mimm/models/classification/alexnet.py
mimm/models/classification/mobilenetv3.py
mimm/models/classification/resnet.py
mimm/models/classification/swin.py
mimm/models/classification/vgg.py
mimm/models/classification/vit.py
mimm-0.0.2.dist-info/METADATA
mimm-0.0.2.dist-info/WHEEL
mimm-0.0.2.dist-info/top_level.txt
mimm-0.0.2.dist-info/RECORD
