Metadata-Version: 2.1
Name: mimm
Version: 0.0.2
Summary: MLX Image Models
Author: Robert McCraith
Author-email: mccraithrobert@gmail.com
Requires-Dist: mlx
